lantern_django/__init__.py
lantern_django/setup.py
lantern_django-0.0.1.dist-info/LICENSE
lantern_django-0.0.1.dist-info/METADATA
lantern_django-0.0.1.dist-info/WHEEL
lantern_django-0.0.1.dist-info/top_level.txt
lantern_django-0.0.1.dist-info/RECORD
